i2x/__init__.py
i2x/api.py
i2x/bes_hca.py
i2x/bes_queue.py
i2x/bes_upgrades.py
i2x/der_choices.py
i2x/der_monitor.py
i2x/der_panel.py
i2x/mpow_utilities.py
i2x/opendss_graph.py
i2x/opendss_interface.py
i2x/pcc_analysis.py
i2x/plot_opendss_feeder.py
i2x/version.py
i2x/der_hca/PlotUtils.py
i2x/der_hca/__init__.py
i2x/der_hca/defaults.json
i2x/der_hca/hca.py
i2x/der_hca/hca_utils.py
i2x/der_hca/islands.py
i2x/der_hca/transformer_costs.csv
i2x/der_hca/upgrade_costs.py
i2x/models/ieee9500/BalancedLoads.dss
i2x/models/ieee9500/BusCoords.dss
i2x/models/ieee9500/CableData.dss
i2x/models/ieee9500/CapControls.dss
i2x/models/ieee9500/Capacitors.dss
i2x/models/ieee9500/EnergyStorage.dss
i2x/models/ieee9500/Generators.dss
i2x/models/ieee9500/HCABase.dss
i2x/models/ieee9500/LatLongCoords.dss
i2x/models/ieee9500/LineCodes.dss
i2x/models/ieee9500/LineGeometry.dss
i2x/models/ieee9500/LinesSwitchesGeometry.dss
i2x/models/ieee9500/LinesSwitchesLineCodes.dss
i2x/models/ieee9500/LoadXfmrCodes.dss
i2x/models/ieee9500/Master-bal-initial-config.dss
i2x/models/ieee9500/Master-unbal-initial-config.dss
i2x/models/ieee9500/Network.json
i2x/models/ieee9500/PNNL-33471.pdf
i2x/models/ieee9500/PV_10pen_DSSPV.dss
i2x/models/ieee9500/PV_NN_100_DSSPV.dss
i2x/models/ieee9500/README.md
i2x/models/ieee9500/Regulators.dss
i2x/models/ieee9500/Transformers.dss
i2x/models/ieee9500/TriplexLineCodes.dss
i2x/models/ieee9500/TriplexLines.dss
i2x/models/ieee9500/UnbalancedLoads.dss
i2x/models/ieee9500/WireData.dss
i2x/models/ieee9500/clean.bat
i2x/models/ieee9500/ieee9500bal.dss
i2x/models/ieee9500/ieee9500unbal.dss
i2x/models/ieee9500/protection.dss
i2x/models/ieee9500/reclosers.dss
i2x/models/ieee9500/switches.dss
i2x/models/ieee_lvn/HCABase.dss
i2x/models/ieee_lvn/Master.dss
i2x/models/ieee_lvn/Network.json
i2x/models/ieee_lvn/README.md
i2x/models/ieee_lvn/SecPar.dss
i2x/models/ieee_lvn/buscoords.dat
i2x/models/ieee_lvn/clean.bat
i2x/models/ieee_lvn/energy_meters.dss
i2x-1.1.4.dist-info/LICENSE.txt
i2x-1.1.4.dist-info/METADATA
i2x-1.1.4.dist-info/WHEEL
i2x-1.1.4.dist-info/entry_points.txt
i2x-1.1.4.dist-info/top_level.txt
i2x-1.1.4.dist-info/RECORD
