Metadata-Version: 2.1
Name: i2x
Version: 1.1.4
Summary: i2x: Interconnection Innovation e-Xchange Open Test Systems.
Home-page: https://github.com/pnnl/i2x
Author: Tom McDermott, Eran Schweitzer
Author-email: Thomas.McDermott@PNNL.gov
License: BSD
Project-URL: Bug Tracker, https://github.com/pnnl/i2x/issues
Classifier: License :: OSI Approved :: BSD License
Classifier: Operating System :: OS Independent
Classifier: Programming Language :: Python :: 3.10
Classifier: Development Status :: 4 - Beta
Classifier: Environment :: Console
Classifier: Intended Audience :: Developers
Classifier: Intended Audience :: Education
Classifier: Intended Audience :: Science/Research
Classifier: Topic :: Scientific/Engineering
License-File: LICENSE.txt
Requires-Dist: matplotlib >=3.5.2
Requires-Dist: networkx >=2.8.4
Requires-Dist: pandas >=1.5.3
Requires-Dist: plotly >=5.9.0
Requires-Dist: requests >=2.28.0 ; platform_system == "Windows"
Requires-Dist: py-dss-interface >=2.0.2 ; platform_system == "Windows"
